TCLIService/TCLIService.py
TCLIService/__init__.py
TCLIService/constants.py
TCLIService/ttypes.py
pyhive/__init__.py
pyhive/common.py
pyhive/exc.py
pyhive/hive.py
pyhive/presto.py
pyhive/sasl_compat.py
pyhive/sqlalchemy_hive.py
pyhive/sqlalchemy_presto.py
pyhive/sqlalchemy_trino.py
pyhive/trino.py
PyHive6si-0.0.5.dev0.dist-info/LICENSE
PyHive6si-0.0.5.dev0.dist-info/METADATA
PyHive6si-0.0.5.dev0.dist-info/WHEEL
PyHive6si-0.0.5.dev0.dist-info/entry_points.txt
PyHive6si-0.0.5.dev0.dist-info/top_level.txt
PyHive6si-0.0.5.dev0.dist-info/RECORD
