Metadata-Version: 2.1
Name: PyHive6si
Version: 0.0.5.dev0
Summary: Python interface to Hive
Home-page: https://github.com/dropbox/PyHive
Author: abhishek gupta
Author-email: abhishek.gupta@6sense.com
License: Apache License, Version 2.0
Platform: UNKNOWN
Classifier: Intended Audience :: Developers
Classifier: License :: OSI Approved :: Apache Software License
Classifier: Operating System :: OS Independent
Classifier: Topic :: Database :: Front-Ends
License-File: LICENSE
Requires-Dist: future
Requires-Dist: python-dateutil
Provides-Extra: hive
Requires-Dist: sasl (>=0.2.1) ; extra == 'hive'
Requires-Dist: thrift (>=0.13.0) ; extra == 'hive'
Requires-Dist: thrift-sasl (>=0.1.0) ; extra == 'hive'
Provides-Extra: hive_pure_sasl
Requires-Dist: pure-sasl (>=0.6.2) ; extra == 'hive_pure_sasl'
Requires-Dist: thrift (>=0.10.0) ; extra == 'hive_pure_sasl'
Requires-Dist: thrift-sasl (>=0.1.0) ; extra == 'hive_pure_sasl'
Provides-Extra: kerberos
Requires-Dist: requests-kerberos (>=0.12.0) ; extra == 'kerberos'
Provides-Extra: presto
Requires-Dist: requests (>=1.0.0) ; extra == 'presto'
Provides-Extra: sqlalchemy
Requires-Dist: sqlalchemy (>=1.3.0) ; extra == 'sqlalchemy'
Provides-Extra: trino
Requires-Dist: requests (>=1.0.0) ; extra == 'trino'
